[
  {
    "Faculty/Staff": "Faculty",
    "Name": "Anderson, Brandi, LICSW, SSW, CFSW, RYT",
    "Title": "Director of the I. DeQuincey Newman Institute and Director of Innovative ACCESS (Access, Culture, Community Engagement, and Student Success)",
    "Secondary Title": "",
    "Phone": "777-2064",
    "Email": "bbrisker@email.sc.edu",
    "Keywords": "",
    "Department": "",
    "College": "College of Social Work"
  },
  {
    "Faculty/Staff": "Faculty",
    "Name": "Bell, Nathaniel",
    "Title": "Director of Research and Evaluation",
    "Secondary Title": "",
    "Phone": "803-576-6781",
    "Email": "nateb@mailbox.sc.edu",
    "Keywords": "",
    "Department": "IFS/IHPR Institute for Families in Society",
    "College": "College of Social Work"
  },
  {
    "Faculty/Staff": "Faculty",
    "Name": "Bosio-McArdle, Jennifer , MSW",
    "Title": "Interim Undergraduate Program Director/Lecturer",
    "Secondary Title": "",
    "Phone": "803-777-0383",
    "Email": "bosio@mailbox.sc.edu",
    "Keywords": "",
    "Department": "",
    "College": "College of Social Work"
  },
  {
    "Faculty/Staff": "Faculty",
    "Name": "Browne, Teri, Ph.D., MSW",
    "Title": "Dean",
    "Secondary Title": "Professor",
    "Phone": "803-777-6258",
    "Email": "brownetm@mailbox.sc.edu",
    "Keywords": "professor, academic, teri, browne, associate, dean, faculty, research",
    "Department": "",
    "College": "College of Social Work"
  },
  {
    "Faculty/Staff": "Staff",
    "Name": "Carter-Moore, Felissa",
    "Title": "Assistant Dean for Finance and Administration",
    "Secondary Title": "",
    "Phone": "803-777-3349",
    "Email": "fcarter@mailbox.sc.edu",
    "Keywords": "administrative, dean, finance, administration",
    "Department": "",
    "College": "College of Social Work"
  },
  {
    "Faculty/Staff": "Staff",
    "Name": "Cato, Camea, M.Ed.",
    "Title": "Graduate Academic Advisor",
    "Secondary Title": "",
    "Phone": "803-777-6492",
    "Email": "catocam@mailbox.sc.edu",
    "Keywords": "",
    "Department": "",
    "College": "College of Social Work"
  },
  {
    "Faculty/Staff": "Faculty",
    "Name": "Cook, Lana, LMSW",
    "Title": "Clinical Senior Lecturer, Director of Assessment & Compliance",
    "Secondary Title": "",
    "Phone": "803-777-9469",
    "Email": "lanac@mailbox.sc.edu",
    "Keywords": "",
    "Department": "",
    "College": "College of Social Work"
  },
  {
    "Faculty/Staff": "Staff",
    "Name": "Cote, Steven",
    "Title": "Director of Enrollment",
    "Secondary Title": "",
    "Phone": "803-777-3372",
    "Email": "scote@mailbox.sc.edu",
    "Keywords": "steven, cote, recruiter",
    "Department": "",
    "College": "College of Social Work"
  },
  {
    "Faculty/Staff": "Staff",
    "Name": "Crawford, Kimberly",
    "Title": "Field Education Placement Manager",
    "Secondary Title": "",
    "Phone": "803-777-3599",
    "Email": "crawfo22@mailbox.sc.edu",
    "Keywords": "",
    "Department": "",
    "College": "College of Social Work"
  },
  {
    "Faculty/Staff": "Faculty",
    "Name": "DeHart, Dana, Ph.D.",
    "Title": "Research Professor Emerita",
    "Secondary Title": "",
    "Phone": "803-777-7867",
    "Email": "dana.dehart@sc.edu",
    "Keywords": "dean, research, professor, dana, dehart",
    "Department": "",
    "College": "College of Social Work"
  },
  {
    "Faculty/Staff": "Faculty",
    "Name": "DiNovo, Rhonda, LMSW",
    "Title": "Assistant Professor / MSW Program Director",
    "Secondary Title": "Director, Graduate Certificate in Drug and Addiction Studies Coordinator; and Continuing Education in Psychodiagnostics, Psychopathology and Ethics",
    "Phone": "803-777-9374",
    "Email": "dinovo@mailbox.sc.edu",
    "Keywords": "Rhonda, DiNovo, Clinical, Professor, MSW Program Director",
    "Department": "",
    "College": "College of Social Work"
  },
  {
    "Faculty/Staff": "Faculty",
    "Name": "Doering-White, John, Ph.D., MSW",
    "Title": "Assistant Professor",
    "Secondary Title": "",
    "Phone": "803-777-7252",
    "Email": "doeringj@mailbox.sc.edu",
    "Keywords": "Doering-White, College of Social Work, Ph.D., MSW",
    "Department": "",
    "College": "College of Social Work"
  },
  {
    "Faculty/Staff": "Staff",
    "Name": "Eggerud, Jillian, LMSW",
    "Title": "Enrollment Management Specialist",
    "Secondary Title": "",
    "Phone": "803-777-9453",
    "Email": "eggerud@mailbox.sc.edu",
    "Keywords": "enrollment, jillian, eggerud",
    "Department": "",
    "College": "College of Social Work"
  },
  {
    "Faculty/Staff": "Staff",
    "Name": "Epps, Ja-Nae, MASCL",
    "Title": "Development and Alumni Relations",
    "Secondary Title": "",
    "Phone": "803-777-7185",
    "Email": "jmepps0@mailbox.sc.edu",
    "Keywords": "development, alumni, events",
    "Department": "",
    "College": "College of Social Work"
  },
  {
    "Faculty/Staff": "Faculty",
    "Name": "Fairweather, Scott, LISW-CP, LCSW, MAC",
    "Title": "Lecturer",
    "Secondary Title": "",
    "Phone": "777-7753",
    "Email": "fairweat@mailbox.sc.edu",
    "Keywords": "",
    "Department": "",
    "College": "College of Social Work"
  },
  {
    "Faculty/Staff": "Faculty",
    "Name": "Farber, Naomi, Ph.D., MSW, ACSW",
    "Title": "Associate Professor",
    "Secondary Title": "",
    "Phone": "803-777-8816",
    "Email": "naomif@mailbox.sc.edu",
    "Keywords": "Naomi, Farber, MSW, Associate, Professor",
    "Department": "",
    "College": "College of Social Work"
  },
  {
    "Faculty/Staff": "Faculty",
    "Name": "Flynn, Cynthia, Ph.D.",
    "Title": "Research Coordinator",
    "Secondary Title": "Assistant Research Professor",
    "Phone": "803-777-1378",
    "Email": "cynthiaf@mailbox.sc.edu",
    "Keywords": "Cynthia, Flynn, Child, Family, Studies",
    "Department": "The Center for Child and Family Studies",
    "College": "College of Social Work"
  },
  {
    "Faculty/Staff": "Faculty",
    "Name": "Fram, Maryah, Ph.D., MSW",
    "Title": "Associate Professor",
    "Secondary Title": "",
    "Phone": "803-777-5945",
    "Email": "fram@mailbox.sc.edu",
    "Keywords": "Maryah, Fram, Professor",
    "Department": "",
    "College": "College of Social Work"
  },
  {
    "Faculty/Staff": "Faculty",
    "Name": "Gowdy, Ann, Ph.D, LISW-CP, MSW",
    "Title": "Lecturer",
    "Secondary Title": "",
    "Phone": "777-6993",
    "Email": "EGOWDY@mailbox.sc.edu",
    "Keywords": "",
    "Department": "",
    "College": "College of Social Work"
  },
  {
    "Faculty/Staff": "Faculty",
    "Name": "Grace, Breanne, Ph.D.",
    "Title": "Associate Professor",
    "Secondary Title": "",
    "Phone": "803-777-9911",
    "Email": "breanneg@mailbox.sc.edu",
    "Keywords": "Breanne, Grace, Associate, Professor",
    "Department": "",
    "College": "College of Social Work"
  },
  {
    "Faculty/Staff": "Faculty",
    "Name": "Hock, Robert, Ph.D., LMSW",
    "Title": "Associate Professor",
    "Secondary Title": "",
    "Phone": "803-777-5861",
    "Email": "roberth@mailbox.sc.edu",
    "Keywords": "",
    "Department": "",
    "College": "College of Social Work"
  },
  {
    "Faculty/Staff": "Staff",
    "Name": "Hougham, Gwendolyn",
    "Title": "Grants Administrator",
    "Secondary Title": "",
    "Phone": "803 777-5292",
    "Email": "houghamg@mailbox.sc.edu",
    "Keywords": "",
    "Department": "",
    "College": "College of Social Work"
  },
  {
    "Faculty/Staff": "Faculty",
    "Name": "Hunter, Stephanie , DSW, LMSW",
    "Title": "Assistant Professor",
    "Secondary Title": "",
    "Phone": "",
    "Email": "SGHUNTER@mailbox.sc.edu",
    "Keywords": "",
    "Department": "",
    "College": "College of Social Work"
  },
  {
    "Faculty/Staff": "Faculty",
    "Name": "Iachini, Aidyn, Ph.D., MSW, LSW",
    "Title": "Professor, Associate Dean of Research",
    "Secondary Title": "",
    "Phone": "803-777-2373",
    "Email": "iachini@mailbox.sc.edu",
    "Keywords": "Aidyn, Iachini, Professor",
    "Department": "",
    "College": "College of Social Work"
  },
  {
    "Faculty/Staff": "Staff",
    "Name": "Jackson, Atavia",
    "Title": "Human Resources Coordinator",
    "Secondary Title": "",
    "Phone": "803-777-3906",
    "Email": "jacksoal@mailbox.sc.edu",
    "Keywords": "Atavia Jackson, human resources",
    "Department": "",
    "College": "College of Social Work"
  },
  {
    "Faculty/Staff": "Staff",
    "Name": "Johnson, Shania, BS",
    "Title": "Assistant to the Associate Dean of Curriculum",
    "Secondary Title": "",
    "Phone": "803.777.9077",
    "Email": "shaniamj@mailbox.sc.edu",
    "Keywords": "",
    "Department": "",
    "College": "College of Social Work"
  },
  {
    "Faculty/Staff": "Staff",
    "Name": "Lail, Avril T., LMSW",
    "Title": "Interim Director of Field Education",
    "Secondary Title": "",
    "Phone": "803-777-3702",
    "Email": "lail@mailbox.sc.edu",
    "Keywords": "",
    "Department": "",
    "College": "College of Social Work"
  },
  {
    "Faculty/Staff": "Faculty",
    "Name": "Levkoff, Sue, ScD, MSW, SM",
    "Title": "Professor",
    "Secondary Title": "",
    "Phone": "803-777-4521",
    "Email": "slevkoff@mailbox.sc.edu",
    "Keywords": "Sue, Levkoff, Professor",
    "Department": "",
    "College": "College of Social Work"
  },
  {
    "Faculty/Staff": "Faculty",
    "Name": "Lopez-De Fede, Ana, Ph.D",
    "Title": "Distinguished Research Professor Emerita, Institute for Famililes in Society",
    "Secondary Title": "",
    "Phone": "803-777-5789",
    "Email": "adefede@mailbox.sc.edu",
    "Keywords": "",
    "Department": "",
    "College": "College of Social Work"
  },
  {
    "Faculty/Staff": "Staff",
    "Name": "Luke, Parthenia",
    "Title": "Bridge to Faculty Postdoctoral Fellow",
    "Secondary Title": "",
    "Phone": "777-3701",
    "Email": "LUKEP@email.sc.edu",
    "Keywords": "",
    "Department": "",
    "College": "College of Social Work"
  },
  {
    "Faculty/Staff": "Staff",
    "Name": "Malloy, Tamara",
    "Title": "Assistant to the Dean",
    "Secondary Title": "",
    "Phone": "803-777-9434",
    "Email": "tmalloy@mailbox.sc.edu",
    "Keywords": "",
    "Department": "",
    "College": "College of Social Work"
  },
  {
    "Faculty/Staff": "Staff",
    "Name": "Marshall, Lynda",
    "Title": "Learning Experience Designer",
    "Secondary Title": "",
    "Phone": "",
    "Email": "LYNDAM@mailbox.sc.edu",
    "Keywords": "",
    "Department": "",
    "College": "College of Social Work"
  },
  {
    "Faculty/Staff": "Staff",
    "Name": "May, Anna, MSW",
    "Title": "Undergraduate Academic Advisor",
    "Secondary Title": "Instructor, UNIV 150 & 151",
    "Phone": "803-777-1545",
    "Email": "MAY8@mailbox.sc.edu",
    "Keywords": "",
    "Department": "",
    "College": "College of Social Work"
  },
  {
    "Faculty/Staff": "Staff",
    "Name": "Montgomery, Victoria, MMC",
    "Title": "Assistant Dean for External Affairs",
    "Secondary Title": "",
    "Phone": "803-777-9462",
    "Email": "vmontgom@mailbox.sc.edu",
    "Keywords": "victoria, montgomery, executive, assistant, president, AASWSW",
    "Department": "Dean's Office",
    "College": "College of Social Work"
  },
  {
    "Faculty/Staff": "Staff",
    "Name": "Moore, Nicholas",
    "Title": "Web Communications/Creative Services Manager",
    "Secondary Title": "",
    "Phone": "803-777-6245",
    "Email": "ntm1@email.sc.edu",
    "Keywords": "",
    "Department": "",
    "College": "College of Social Work"
  },
  {
    "Faculty/Staff": "Faculty",
    "Name": "Morgan, Candice, Ph.D., MSW",
    "Title": "Assistant Professor",
    "Secondary Title": "Instructor",
    "Phone": "803-777-9456",
    "Email": "morgancr@email.sc.edu",
    "Keywords": "Candice Morgan, Greenville, social work, instructor, MSW, coordinator",
    "Department": "",
    "College": "College of Social Work"
  },
  {
    "Faculty/Staff": "Staff",
    "Name": "Morris, Dale",
    "Title": "Administrative Assistant",
    "Secondary Title": "",
    "Phone": "803-777-5291",
    "Email": "morris5@mailbox.sc.edu",
    "Keywords": "administrative",
    "Department": "",
    "College": "College of Social Work"
  },
  {
    "Faculty/Staff": "Staff",
    "Name": "Osborne, Morgan, MSW",
    "Title": "Field Education Placement Manager",
    "Secondary Title": "",
    "Phone": "803-777-9820",
    "Email": "angelao@mailbox.sc.edu",
    "Keywords": "",
    "Department": "",
    "College": "College of Social Work"
  },
  {
    "Faculty/Staff": "Faculty",
    "Name": "Ottone, Michael, LISW-CP, CPM",
    "Title": "Interim Undergraduate Program Director, Senior Instructor",
    "Secondary Title": "Coordinator, Combination Degree Programs and Non-Credit Continuing Education Courses",
    "Phone": "803-777-5563",
    "Email": "ottone@mailbox.sc.edu",
    "Keywords": "Michael, Ottone, Clinical, Instructor",
    "Department": "",
    "College": "College of Social Work"
  },
  {
    "Faculty/Staff": "Faculty",
    "Name": "Owens, Shaun, Ph.D., MPH",
    "Title": "Associate Professor",
    "Secondary Title": "",
    "Phone": "803-777-0384",
    "Email": "owenso@mailbox.sc.edu",
    "Keywords": "Shaun, Owens, Professor",
    "Department": "",
    "College": "College of Social Work"
  },
  {
    "Faculty/Staff": "Faculty",
    "Name": "Penney, Patrice, MSW, LISW-CP-S, Approved Supervisor",
    "Title": "Assistant Professor, Coordinator, Trauma-Informed Practice Certificate",
    "Secondary Title": "",
    "Phone": "803-777-9461",
    "Email": "patricep@mailbox.sc.edu",
    "Keywords": "Patrice, Penney, Clinical, Professor",
    "Department": "",
    "College": "College of Social Work"
  },
  {
    "Faculty/Staff": "Faculty",
    "Name": "Popa-Mabe, Melania , Ph.D.",
    "Title": "Associate Professor",
    "Secondary Title": "",
    "Phone": "803-777-3906",
    "Email": "melania@mailbox.sc.edu",
    "Keywords": "Melania, Popa-Mabe, clinical, professor",
    "Department": "",
    "College": "College of Social Work"
  },
  {
    "Faculty/Staff": "Faculty",
    "Name": "Price, Janay , MSW, LISW-CP",
    "Title": "Lecturer",
    "Secondary Title": "",
    "Phone": "",
    "Email": "JANAYP@mailbox.sc.edu",
    "Keywords": "",
    "Department": "",
    "College": "College of Social Work"
  },
  {
    "Faculty/Staff": "Faculty",
    "Name": "Roth, Benjamin, Ph.D., MSW",
    "Title": "Associate Dean for Curriculum",
    "Secondary Title": "",
    "Phone": "803-777-9352",
    "Email": "rothbj@sc.edu",
    "Keywords": "Benjamin, Roth, Professor",
    "Department": "",
    "College": "College of Social Work"
  },
  {
    "Faculty/Staff": "Faculty",
    "Name": "Seay, Kristen, Ph.D., MSW",
    "Title": "PhD Program Director",
    "Secondary Title": "",
    "Phone": "803-777-4221",
    "Email": "kdseay@mailbox.sc.edu",
    "Keywords": "Kristen, Seay, Professor, associate, ph.d.",
    "Department": "",
    "College": "College of Social Work"
  },
  {
    "Faculty/Staff": "Faculty",
    "Name": "Shapiro, Cheri, Ph.D.",
    "Title": "Director, Institute for Families in Society",
    "Secondary Title": "Research Associate Professor",
    "Phone": "803-777-8760",
    "Email": "cshapiro@mailbox.sc.edu",
    "Keywords": "Cheri, Shapiro, Research, Professor",
    "Department": "",
    "College": "College of Social Work"
  },
  {
    "Faculty/Staff": "Staff",
    "Name": "Singleton, Sonya",
    "Title": "Assistant Dean for Students",
    "Secondary Title": "",
    "Phone": "803-777-9436",
    "Email": "sonya.singleton@sc.edu",
    "Keywords": "dean, students",
    "Department": "",
    "College": "College of Social Work"
  },
  {
    "Faculty/Staff": "Staff",
    "Name": "Steen, Isabel , LMSW",
    "Title": "Assistant Director of Development",
    "Secondary Title": "",
    "Phone": "704-608-9562",
    "Email": "isabel.steen@sc.edu",
    "Keywords": "development",
    "Department": "",
    "College": "College of Social Work"
  },
  {
    "Faculty/Staff": "Staff",
    "Name": "Strickland, Mary Grace, LMSW",
    "Title": "Program Recruiter",
    "Secondary Title": "",
    "Phone": "(803)777-9909",
    "Email": "mgs8@email.sc.edu",
    "Keywords": "recruit, enrollment",
    "Department": "",
    "College": "College of Social Work"
  },
  {
    "Faculty/Staff": "Staff",
    "Name": "Walker, Bianca, MSP, MSFP",
    "Title": "Graduate Academic Advisor",
    "Secondary Title": "",
    "Phone": "803-777-9258",
    "Email": "Bw96@mailbox.sc.edu",
    "Keywords": "",
    "Department": "",
    "College": "College of Social Work"
  },
  {
    "Faculty/Staff": "Staff",
    "Name": "White, Stephanie W.",
    "Title": "Senior Director of Development",
    "Secondary Title": "",
    "Phone": "803-777-8220",
    "Email": "sbw5@mailbox.sc.edu",
    "Keywords": "",
    "Department": "",
    "College": "College of Social Work"
  },
  {
    "Faculty/Staff": "Staff",
    "Name": "Williams, Brantley",
    "Title": "IT and Building Coordinator",
    "Secondary Title": "",
    "Phone": "803-777-9701",
    "Email": "williabe@email.sc.edu",
    "Keywords": "",
    "Department": "",
    "College": "College of Social Work"
  },
  {
    "Faculty/Staff": "Faculty",
    "Name": "Wilson, Betty  L., PhD, MSW",
    "Title": "Assistant Professor",
    "Secondary Title": "",
    "Phone": "",
    "Email": "WILSO479@email.sc.edu",
    "Keywords": "",
    "Department": "",
    "College": "College of Social Work"
  },
  {
    "Faculty/Staff": "Faculty",
    "Name": "Wolfer, Terry, Ph.D., MSW",
    "Title": "Professor",
    "Secondary Title": "",
    "Phone": "803-777-9486",
    "Email": "terryw@mailbox.sc.edu",
    "Keywords": "Terry, Wolfer, Professor",
    "Department": "",
    "College": "College of Social Work"
  },
  {
    "Faculty/Staff": "Faculty",
    "Name": "Woo, Bongki , Ph.D.",
    "Title": "Associate Professor",
    "Secondary Title": "",
    "Phone": "803-777-3511",
    "Email": "woob@mailbox.sc.edu",
    "Keywords": "Bongki, Woo, professor",
    "Department": "",
    "College": "College of Social Work"
  },
  {
    "Faculty/Staff": "Faculty",
    "Name": "Wooten, Nikki, PhD, LISW-CP",
    "Title": "Associate Professor",
    "Secondary Title": "Coordinator, Social and Behavioral Health with Military Members, Veterans and Military Families Certificate program",
    "Phone": "803-777-2973",
    "Email": "wootennr@mailbox.sc.edu",
    "Keywords": "Nikki, Wooten, Professor",
    "Department": "",
    "College": "College of Social Work"
  },
  {
    "Faculty/Staff": "Faculty",
    "Name": "Wright, Margriet de Zeeuw, Ph.D., MSW",
    "Title": "Associate Professor",
    "Secondary Title": "MSW Charleston Site Coordinator",
    "Phone": "803-777-7178",
    "Email": "margriet@mailbox.sc.edu",
    "Keywords": "Margriet, de, Zeeuw, Wright, Clinical, Professor, MSW, Charleston, site, coordinator",
    "Department": "",
    "College": "College of Social Work"
  },
  {
    "Faculty/Staff": "Faculty",
    "Name": "Xu, Yanfeng, Ph.D., MSW",
    "Title": "Assistant Professor",
    "Secondary Title": "",
    "Phone": "803-777-2215",
    "Email": "yanfeng@mailbox.sc.edu",
    "Keywords": "College of Social Work, Yanfeng, Xu, Ph.D., MSW",
    "Department": "",
    "College": "College of Social Work"
  }
]
